README
setup.py
bambu_pages/__init__.py
bambu_pages/admin.py
bambu_pages/apps.py
bambu_pages/helpers.py
bambu_pages/models.py
bambu_pages/querysets.py
bambu_pages/search_indexes.py
bambu_pages/sitemaps.py
bambu_pages/urls.py
bambu_pages/views.py
bambu_pages.egg-info/PKG-INFO
bambu_pages.egg-info/SOURCES.txt
bambu_pages.egg-info/dependency_links.txt
bambu_pages.egg-info/requires.txt
bambu_pages.egg-info/top_level.txt
bambu_pages/migrations/0001_initial.py
bambu_pages/migrations/__init__.py
bambu_pages/templates/pages/page.html
bambu_pages/templates/pages/sidebar.inc.html
bambu_pages/templates/search/indexes/bambu_pages/page_text.txt