Metadata-Version: 1.1
Name: bambu-pages
Version: 3.3
Summary: Tools for Django webapps
Home-page: https://github.com/iamsteadman/bambu-pages
Author: Steadman
Author-email: mark@steadman.io
License: UNKNOWN
Platform: UNKNOWN
Classifier: Development Status :: 4 - Beta
Classifier: Environment :: Web Environment
Classifier: Framework :: Django
